langchain_mcp_connect/__init__.py
langchain_mcp_connect/langchain_mcp.py
langchain_mcp_connect/py.typed
langchain_mcp_connect/data_models/__init__.py
langchain_mcp_connect/data_models/mcp_servers.py
langchain_mcp_connect-2.2.0.dist-info/METADATA
langchain_mcp_connect-2.2.0.dist-info/WHEEL
langchain_mcp_connect-2.2.0.dist-info/licenses/LICENSE
langchain_mcp_connect-2.2.0.dist-info/RECORD
