Metadata-Version: 2.4
Name: langchain-mcp-connect
Version: 2.2.0
Summary: Model context protocol connector for LangChain
Project-URL: GitHub, https://github.com/lloydhamilton/langchain_mcp_connect
Project-URL: Issues, https://github.com/lloydhamilton/langchain_mcp_connect/issues
Author-email: Lloyd Hamilton <lloydhamilton1991@gmail.com>
License-File: LICENSE
Requires-Python: >=3.11
Requires-Dist: jsonschema-pydantic==0.6
Requires-Dist: langchain-core>=0.3.30
Requires-Dist: mcp>=1.2.0
